{
  "contact": {
    "entity": "Centre D'Études Et De Prospective",
    "firstname": "Julia",
    "lastname": "Gassie"
  },
  "continent": [
    "europe"
  ],
  "country": [
    "france"
  ],
  "createdAt": 1662722076,
  "date": [
    "2020-09-11"
  ],
  "description": "Les sources d'information et les enquêtes sur les comportements alimentaires apportent souvent de précieux résultats, mais elles souffrent aussi de biais créant parfois des décalages entre comportements déclarés et réels. Non spécifiques à l'alimentation, ces écarts sont liés aux caractéristiques des répondants, aux contextes de leurs réponses, aux démarches et méthodes de recueil des informations et à leurs modalités ultérieures de traitement. Du fait de leurs impacts potentiels sur le pilotage de l'action publique, le ministère de l’Agriculture et de l’Alimentation, l’ADEME et FranceAgriMer ont souhaité commander une étude sur ce sujet. Cette note présente les principaux enseignements de ce travail.",
  "field": [
    "economics-statistics",
    "sociology"
  ],
  "lang": "fr",
  "location": "",
  "name": "Les écarts entre alimentation déclarée et alimentation réelle : observations et explications",
  "pubId": 410652,
  "score": 1004.1222222222162,
  "state": "completed-project",
  "status": "verified",
  "team": [
    {
      "entity": "Centre D'Études Et De Prospective",
      "firstname": "Julia",
      "lastname": "Gassie"
    }
  ],
  "thematic": [
    "food-agriculture-fishery",
    "human-behaviours-social-relations",
    "consumption-and-production-patterns",
    "public-policy-evaluation-impact"
  ],
  "time": "",
  "type": [
    "report"
  ],
  "url": "https://agriculture.gouv.fr/les-ecarts-entre-alimentation-declaree-et-alimentation-reelle-observations-et-explications-analyse",
  "yt": "",
  "zone": [
    3,
    1
  ],
  "lastEvent": {
    "at": 1662802074,
    "by": {
      "$oid": "62b1ee8fab64fe00092bf7c4"
    }
  },
  "ref": [
    {
      "$oid": "62b1ee8fab64fe00092bf7c4"
    }
  ],
  "verified": [
    {
      "by": {
        "$oid": "62b1ee8fab64fe00092bf7c4"
      },
      "at": 1662802074,
      "content": null
    }
  ]
}