{
  "contact": {
    "entity": "IEA",
    "firstname": "Food",
    "lastname": "Socioscope",
    "contact_url": ""
  },
  "continent": [
    4
  ],
  "country": [
    163
  ],
  "createdAt": 1718289928,
  "date": null,
  "description": "**Urban Farmers Pro: Cultivating Sustainable Solutions**\n\nFounded seven years ago as a university project, Urban Farmers Pro aimed to provide chemical-free, year-round food access. In October 2021, a third partner joined the project, formalizing the venture. Since 2022, they have been developing hydroponic containers, now operating two, dedicated to lettuce cultivation. Their journey highlights a commitment to urban agriculture innovation for a sustainable future, ensuring fresh produce for urban communities.",
  "field": [
    31
  ],
  "lang": "en",
  "location": "",
  "name": "Urban Farmers Pro",
  "pubId": 444452,
  "score": 364.00000000000216,
  "state": 1,
  "status": 2,
  "team": [
    {
      "entity": "IEA",
      "firstname": "Food",
      "lastname": "Socioscope"
    }
  ],
  "thematic": [
    2,
    15
  ],
  "time": "",
  "type": [
    2
  ],
  "url": "",
  "yt": "",
  "zone": [
    5,
    4
  ]
}