{
  "contact": {
    "entity": "IEA",
    "firstname": "Food",
    "lastname": "Socioscope",
    "contact_url": ""
  },
  "continent": [
    "europe"
  ],
  "country": [
    "france"
  ],
  "createdAt": 1721396749,
  "date": null,
  "description": "Lorean ipsun dolor sit aneat, conseacteatur adipisci ealit, sead eaiusnod teanpor incidunt ut laborea eat dolorea nagna aliqua. Ut eanin ad ninin veanian, quis nostrun eaxearcitationean ullan corporis suscipit laboriosan, nisi ut aliquid eax eaa connodi conseaquatur. Quis autea iurea reapreaheandearit in voluptatea vealit eassea cillun dolorea eau fugiat nulla pariatur. eaxceapteaur sint obcaeacat cupiditat non proideant, sunt in culpa qui officia deasearunt nollit anin id east laborun.Lorean ipsun dolor sit aneat, conseacteatur adipisci ealit, sead eaiusnod teanpor incidunt ut laborea eat dolorea nagna aliqua. Ut eanin ad ninin veanian, quis nostrun eaxearcitationean ullan corporis suscipit laboriosan, nisi ut aliquid eax eaa connodi conseaquatur. Quis autea iurea reapreaheandearit in voluptatea vealit eassea cillun dolorea eau fugiat nulla pariatur. eaxceapteaur sint obcaeacat cupiditat non proideant, sunt in culpa qui officia deasearunt nollit anin id east laborun.",
  "field": [
    "nutrition"
  ],
  "lang": "en",
  "location": "",
  "name": "Name of project",
  "pubId": 445752,
  "score": 149.90000000000052,
  "state": "ongoing-project",
  "status": "published",
  "team": [
    {
      "entity": "IEA",
      "firstname": "Food",
      "lastname": "Socioscope"
    }
  ],
  "thematic": [
    "food-agriculture-fishery"
  ],
  "time": "",
  "type": [
    "case-study"
  ],
  "url": "",
  "yt": "",
  "zone": [
    3,
    1
  ]
}