{
  "contact": {
    "entity": "IEA",
    "firstname": "Food",
    "lastname": "Socioscope",
    "contact_url": ""
  },
  "continent": [
    4
  ],
  "country": [
    164
  ],
  "createdAt": 1754404252,
  "date": null,
  "description": "Madre Tierra is an initiative based in Quito, Ecuador, founded in 2017 by local neighbors aiming to transform their eating habits through a cooperative model. The cooperative, Suriendo Redes y Sabores, focuses on promoting local, chemical-free, and farmer-based food alternatives. By connecting with various agroecological organizations, Madre Tierra facilitates direct producer-consumer markets, fostering community engagement and access to healthy food while supporting sustainable agricultural practices.",
  "field": [
    31
  ],
  "lang": "en",
  "location": "",
  "name": "Madre Tierra",
  "pubId": 450252,
  "score": -80.08660456592939,
  "state": 1,
  "status": 1,
  "team": [
    {
      "entity": "IEA",
      "firstname": "Food",
      "lastname": "Socioscope"
    }
  ],
  "thematic": [
    2
  ],
  "time": "",
  "type": [
    2
  ],
  "url": "",
  "yt": "",
  "zone": [
    5,
    4
  ]
}