{
  "contact": {
    "entity": "IEA",
    "firstname": "Food",
    "lastname": "Socioscope",
    "contact_url": ""
  },
  "continent": [
    "south-america"
  ],
  "country": [
    "paraguay"
  ],
  "createdAt": 1754384542,
  "date": null,
  "description": "High Farm is an innovative urban farm founded in 2019, focusing on sustainable food production through vertical farming techniques. By cultivating microgreens, edible flowers, and greens in controlled environments, High Farm aims to bring fresh, pesticide-free produce closer to urban consumers. The initiative emphasizes harmony between technology, nature, and society, promoting gastronomic diversity while minimizing environmental impact. With a commitment to research and development, High Farm aspires to be a leader in sustainable agricultural practices in Latin America.",
  "field": [
    "nutrition"
  ],
  "lang": "en",
  "location": "",
  "name": "High Farm",
  "pubId": 457952,
  "score": -225.55397951113932,
  "state": "ongoing-project",
  "status": "published",
  "team": [
    {
      "entity": "IEA",
      "firstname": "Food",
      "lastname": "Socioscope"
    }
  ],
  "thematic": [
    "food-agriculture-fishery"
  ],
  "time": "",
  "type": [
    "case-study"
  ],
  "url": "",
  "yt": "",
  "zone": [
    5,
    4
  ]
}