{
  "contact": {
    "entity": "IEA",
    "firstname": "Food",
    "lastname": "Socioscope",
    "contact_url": ""
  },
  "continent": [
    "north-america"
  ],
  "country": [
    "costa-rica"
  ],
  "createdAt": 1754476018,
  "date": null,
  "description": "The initiative at Rancho Mastatal focuses on regenerative practices, sustainable living, and permaculture education in Costa Rica. Founded by a dedicated team of foreigners, the center offers training programs, apprenticeships, and eco-tourism experiences, fostering a community that emphasizes harmony with nature. With a commitment to local sourcing and community integration, they aim to inspire visitors to adopt sustainable lifestyles, creating a ripple effect that extends beyond their immediate environment.",
  "field": [
    "ecology-environmental-sciences"
  ],
  "lang": "en",
  "location": "",
  "name": "Rancho Mastatal",
  "pubId": 465652,
  "score": -124.88363808334675,
  "state": "ongoing-project",
  "status": "published",
  "team": [
    {
      "entity": "IEA",
      "firstname": "Food",
      "lastname": "Socioscope"
    }
  ],
  "thematic": [
    "ecology-environmental-change"
  ],
  "time": "",
  "type": [
    "case-study"
  ],
  "url": "",
  "yt": "",
  "zone": [
    6,
    3
  ]
}