{
  "contact": {
    "entity": "IEA",
    "firstname": "Food",
    "lastname": "Socioscope",
    "contact_url": ""
  },
  "continent": [
    0
  ],
  "country": [
    34
  ],
  "createdAt": 1754653716,
  "date": null,
  "description": "The initiative focuses on developing a sustainable seaweed farming industry in Sri Lanka, aiming to uplift local communities, particularly women, by providing job opportunities and fair compensation. The project emphasizes innovation through research and development, creating value-added products like CMOS drinks and gummies. By collaborating with local farmers and universities, the initiative seeks to establish a vertically integrated supply chain, enhancing quality control and promoting environmental benefits, while addressing challenges in the agricultural sector.",
  "field": [
    31
  ],
  "lang": "en",
  "location": "",
  "name": "Seashore Garden",
  "pubId": 479052,
  "score": 54.88789808917213,
  "state": 1,
  "status": 1,
  "team": [
    {
      "entity": "IEA",
      "firstname": "Food",
      "lastname": "Socioscope"
    }
  ],
  "thematic": [
    2
  ],
  "time": "",
  "type": [
    2
  ],
  "url": "",
  "yt": "",
  "zone": [
    0,
    0
  ]
}